fm2/__init__.py
fm2/fm2.py
fm2/bin/FileHFM_Isotropic2
fm2/bin/FileHFM_Isotropic3
fm2/bin/input_Data.dat
fm2/bin/input_Format.txt
fm2/bin/output_Data.dat
fm2/bin/output_Format.txt
fm2/entities/__init__.py
fm2/entities/fm2_info.py
fm2/entities/fm2_map.py
fast_marching_square-0.1.1.dist-info/LICENSE
fast_marching_square-0.1.1.dist-info/METADATA
fast_marching_square-0.1.1.dist-info/WHEEL
fast_marching_square-0.1.1.dist-info/top_level.txt
fast_marching_square-0.1.1.dist-info/RECORD
