Metadata-Version: 2.1
Name: fast-marching-square
Version: 0.1.1
Summary: Fast Marching Square (FM2) is a path planning algorithm based on the Fast Marching Method that solves the Eikonal equation.
Author: Vistor
Project-URL: Homepage, https://github.com/vistormu/fast_marching_square
Project-URL: Bug Tracker, https://github.com/vistormu/fast_marching_square/issues
Classifier: Programming Language :: Python :: 3
Classifier: License :: OSI Approved :: MIT License
Classifier: Operating System :: OS Independent
Requires-Python: >=3.10
License-File: LICENSE
Requires-Dist: numpy
Requires-Dist: agd
Requires-Dist: pillow
Requires-Dist: scipy
